cstarmigrate/__init__.py
cstarmigrate/__main__.py
cstarmigrate/cli.py
cstarmigrate/config.py
cstarmigrate/cql.py
cstarmigrate/exceptions.py
cstarmigrate/migration.py
cstarmigrate/migrator.py
cstar_migrate-1.0.0rc2.dist-info/LICENSE
cstar_migrate-1.0.0rc2.dist-info/METADATA
cstar_migrate-1.0.0rc2.dist-info/WHEEL
cstar_migrate-1.0.0rc2.dist-info/entry_points.txt
cstar_migrate-1.0.0rc2.dist-info/top_level.txt
cstar_migrate-1.0.0rc2.dist-info/RECORD
