Metadata-Version: 2.1
Name: cstar-migrate
Version: 1.0.0rc2
Summary: Cassandra schema migration tool
Author-email: Andrey Martyanov <andrey@martyanov.com>
License: Copyright (C) 2020, 2021 Andrey Martyanov
Project-URL: Repository, https://github.com/martyanov/cstar-migrate
Project-URL: Issues, https://github.com/martyanov/cstar-migrate/issues
Keywords: cassandra,schema,migration,tool
Classifier: Development Status :: 4 - Beta
Classifier: Intended Audience :: Developers
Classifier: Intended Audience :: System Administrators
Classifier: License :: OSI Approved :: MIT License
Classifier: Programming Language :: Python :: 3
Classifier: Programming Language :: Python :: 3.8
Classifier: Programming Language :: Python :: 3.9
Classifier: Programming Language :: Python :: 3.10
Classifier: Programming Language :: Python :: 3.11
Classifier: Topic :: Database
Requires-Python: <4,>=3.8
License-File: LICENSE
Requires-Dist: arrow <2,>=0.15
Requires-Dist: cassandra-driver <4,>=3.0
Requires-Dist: pyyaml <7,>=5.1
Requires-Dist: tabulate <0.10,>=0.8
Provides-Extra: dev
Requires-Dist: flake8 ==6.1.0 ; extra == 'dev'
Requires-Dist: flake8-pyproject ==1.2.3 ; extra == 'dev'
Provides-Extra: test
Requires-Dist: pytest-cov ==4.1.0 ; extra == 'test'
Requires-Dist: pytest ==7.4.0 ; extra == 'test'
